{
  "survival": {
    "2000": {
        "BGD": 81.28,
        "DEU": 55.75,
        "USA": 68.16,
        "CHN": 69.03,
        "FRA": 59.63,
        "CHE": 66.05,
        "ESP": 63.43,
        "JPN": 62.27,
        "IND": 85.4,
        "GBR": 62.81,
        "MEX": 88.77,
        "AUS": 71.24,
        "AFG": 85.57,
        "CAN": 66.71,
        "IRN": 87.99,
        "PAK": 84.84,
        "SOM": 87.39,
        "SWE": 68.65,
        "THA": 72.34,
        "BRA": 79.11
    },
    "2005": {
        "BGD": 83.04,
        "DEU": 57.51,
        "USA": 68.56,
        "CHN": 67.02,
        "FRA": 61.58,
        "CHE": 68.12,
        "ESP": 66.7,
        "JPN": 64.89,
        "IND": 84.79,
        "GBR": 64.44,
        "MEX": 88.28,
        "AUS": 71.69,
        "AFG": 85.8,
        "CAN": 67.33,
        "IRN": 87.45,
        "PAK": 84.53,
        "SOM": 87.96,
        "SWE": 66.97,
        "THA": 71.83,
        "BRA": 78.14
      },
    "2010": {
        "BGD": 83.4,
        "DEU": 60.1,
        "USA": 85.38,
        "CHN": 68.09,
        "FRA": 61.14,
        "CHE": 68.59,
        "ESP": 67.03,
        "JPN": 65.63,
        "IND": 84.18,
        "GBR": 66.13,
        "MEX": 88.19,
        "AUS": 72.5,
        "AFG": 85.75,
        "CAN": 67.36,
        "IRN": 86.55,
        "PAK": 84.34,
        "SOM": 88.40,
        "SWE": 70.0,
        "THA": 69.12,
        "BRA": 77.02
      },
    "2015": {
        "BGD": 83.8,
        "DEU": 61.91,
        "USA": 68.09,
        "CHN": 67.2,
        "FRA": 60.5,
        "CHE": 71.03,
        "ESP": 66.29,
        "JPN": 67.94,
        "IND": 83.19,
        "GBR": 67.39,
        "MEX": 87.41,
        "AUS": 73.59,
        "AFG": 85.5,
        "CAN": 67.93,
        "IRN": 84.49,
        "PAK": 83.91,
        "SOM": 70,
        "SWE": 72.86,
        "THA": 65.05,
        "BRA": 75.88
      }
  }
}